{
  "id": "2648438483_1",
  "title": "SeeDAO新加坡 | 邀你参加 SeeDAO 最健康的 Side Event",
  "author": "",
  "link": "https://mp.weixin.qq.com/s/QhIbb43QuvPXyqU1STnzpg",
  "cover": "https://mmbiz.qpic.cn/sz_mmbiz_jpg/TqajLKDg1xW7s7GWrYibuvyhH5P8P42aRtcibLMWB5KQFeXO7fbTibicD0t9GIxqOEr0OmicXibYfK4wdJE1eWNd87Wg/0?wx_fmt=jpeg",
  "digest": "🌏 SeeDAO致力于连接 100 万 Web3 游民的数字城邦，我们的愿景是在基于地缘的民族国家之外，在赛博世界另建一片人类的生存空间。新加坡凭借安全稳定的政治和居住环境，成为全球数字游民的打卡地之一，也汇聚了无数资本和人才的创新中心。\n\n🤝 为了让参加Token2049、以太坊新加坡活动、SuperReturn Asia的小伙伴们更好地产生连接和交流，我们将举行多场篮球和飞盘等运动社交活动，用一种全新的方式，让大家在紧张的大会日程中得到放松，充分感受新加坡的归属感与融合精神。篮球比赛、飞盘对战……这些充满活力的运动，不仅让您挥洒汗水，锻炼身体，更是促进交流与友谊的桥梁。\n\n⏰ 目前暂定的运动社交活动安排：\n▶ 9 Sep 6PM 篮球：新加坡Web3联队 VS 来新Web3游民联队\n▶&nbsp;10 Sep Sun 5PM 飞盘： The Lawn @ Marina Bay (in between The Sail condo and MBFC)\n▶&nbsp;13 Sep Wed 6:15PM 飞盘： The Lawn @ Marina Bay (in between The Sail condo and MBFC)\n▶&nbsp;15 Sep Fri 6:15PM 飞盘： The Lawn @ Marina Bay (in between The Sail condo and MBFC)\n▶&nbsp;16 Sep 6PM 篮球：新加坡创投从业者联队 VS 来新创投从业者联队\n\n活动会根据报名小伙伴的情况，灵活调整，增加更多场次。有计划下个月来新加坡，想一起参与的小伙伴请填写下面信息进行注册。\n\n⚡️ 活动免费参与，名额有限，先到先得！\n🔗 https://forms.gle/TgGZhhKkPYAhY1UD9\n\n内容来源: 新加坡城市联络人Tony\n设计: Mona",
  "publishTime": "2023-08-23 12:13:16",
  "categories": [
    "新加披线下活动"
  ],
  "url": "https://mp.weixin.qq.com/s?__biz=MzI3NDAzMjkwNg==&mid=undefined&idx=undefined&sn=undefined"
}
