{
  "id": "2648433080_1",
  "title": "Web3她声音｜直面野心，我们可以站在舞台中心",
  "author": "",
  "link": "https://mp.weixin.qq.com/s/8BRfMuGOgnrVMEmGPJTGGg",
  "cover": "https://mmbiz.qpic.cn/sz_mmbiz_jpg/TqajLKDg1xX8QTK7pVgkickLDK6aFv2kSBoDzlNrqIgvO5oSa9OciaWHdabmYS0fQowvzcI1yNzBtq8etPupJotg/0?wx_fmt=jpeg",
  "digest": "📢【web3她声音 第五期】\n\nSeeGIRLS于下周二晚九点邀请到 SeeDAO 发起人——唐晗，届时会分享女性创业者 Web3机遇与选择。欢迎各位友友一起来学习~\n\n👩【嘉宾】\n•唐晗：SeeDAO 发起人、女性创业者\n\n🕰️【分享时间】\n•2023/7/18 21:00 (UTC+8)\n\n🌍【相关话题】\n•创办SeeDAO之前的经历？\n•如何进入Web3?\n•关于SeeDAO的创业故事？\n•女性在创业中面临哪些优势和劣势？\n•女性在 DAO 中的角色？\n•女性创业者需要做什么？\n•数字游民的生活习惯or感情生活？\n• …（加入 SeeGIRLS 解锁更多女性话题🥳\n\n也欢迎对SeeGIRLS感兴趣的男性作为观察员和协调员加入~",
  "publishTime": "2023-07-15 14:02:03",
  "categories": [],
  "url": "https://mp.weixin.qq.com/s?__biz=MzI3NDAzMjkwNg==&mid=undefined&idx=undefined&sn=undefined"
}
