{
  "id": "2648414426_3",
  "title": "SeeDAO 日报 | 1月20日:  “离浦人” 离谱魂，一起赚 780ETH 成为人上人",
  "author": "SeeDAO",
  "link": "https://mp.weixin.qq.com/s/zCJB0WQCSCp2qLia5v_HuA",
  "cover": "https://mmbiz.qlogo.cn/mmbiz_jpg/TqajLKDg1xX8qK02SQtXePVic4JUuWzPTOW7iadn5VBUntLIdJVuQyrQDcgJQNQMC94uFjNlzoQPLMFmyzqtYzRg/0?wx_fmt=jpeg",
  "digest": "加入 SeeDAO，探索财富密码。",
  "publishTime": "2022-01-21 12:53:57",
  "categories": [],
  "url": "https://mp.weixin.qq.com/s?__biz=MzI3NDAzMjkwNg==&mid=undefined&idx=undefined&sn=undefined"
}
