{
  "id": "2648454379_1",
  "title": "一个月后，我们的播客怎么样了？| Hello 2024 播客作品长廊",
  "author": "星云Nebula",
  "link": "https://mp.weixin.qq.com/s/-nK6dJYu6CRFCu4KTmVLWw",
  "cover": "https://mmbiz.qpic.cn/sz_mmbiz_jpg/d45NMG5FhbLF8g23DDuG4Qcqx3via3AMZuf9gld0CwicQTEj9xHa8OmQ2pvOzepaibn9e8aDZX2WbgVDBbC2K8wCw/0?wx_fmt=jpeg",
  "digest": "和播客搭子一起共学都会发生什么？",
  "publishTime": "2024-03-28 11:20:35",
  "categories": [],
  "url": "https://mp.weixin.qq.com/s?__biz=MzI3NDAzMjkwNg==&mid=undefined&idx=undefined&sn=undefined"
}
