{
  "id": "2648419208_1",
  "title": "二次方融资的攻守之道：探索 Gitcoin Grants 攻击向量的开放科学计划",
  "author": "weiwei",
  "link": "https://mp.weixin.qq.com/s/-YYfelSCtKMHY0A5ObWemg",
  "cover": "https://mmbiz.qlogo.cn/mmbiz_jpg/TqajLKDg1xV3SlGYDFt7jXzh7W4Er9rN6EpYgiaVhjCdEgs56BxEgequibLFM1R63ZOXYicibqb6zVLicMSGEPiartPg/0?wx_fmt=jpeg",
  "digest": "如何防止薅羊毛大军？",
  "publishTime": "2022-06-20 09:39:17",
  "categories": [
    "公共物品"
  ],
  "url": "https://mp.weixin.qq.com/s?__biz=MzI3NDAzMjkwNg==&mid=undefined&idx=undefined&sn=undefined"
}
