{
  "id": "2648443035_1",
  "title": "SeeGIRLS | 滨口龙介《偶然与想象》观影会",
  "author": "SeeDAO",
  "link": "https://mp.weixin.qq.com/s/buMfzGXMHktIOWP_JM-C-g",
  "cover": "https://mmbiz.qpic.cn/sz_mmbiz_jpg/TqajLKDg1xU0klSic6az3Q8yoarEv8VCGWMiaWUm98KhJlVibzH1K9drU8pJ6svXSork71Cxwz5Gpv8CEq7shMPeg/0?wx_fmt=jpeg",
  "digest": "几周前我们挑选了一部以女性视角讲述故事的电影《偶然与想象》，组织了一次线上观影活动，来和大家一起观影并分享感受。",
  "publishTime": "2023-10-19 15:25:40",
  "categories": [
    "SeeGIRLS",
    "web3女性",
    "SeeDAO"
  ],
  "url": "https://mp.weixin.qq.com/s?__biz=MzI3NDAzMjkwNg==&mid=undefined&idx=undefined&sn=undefined"
}
