{
  "id": "2648456704_1",
  "title": "新闻速递1：国际 Builder 去哪儿？",
  "author": "大地之子定慧",
  "link": "https://mp.weixin.qq.com/s/o0sHWhG9Ls-otf_cX9podA",
  "cover": "https://mmbiz.qpic.cn/sz_mmbiz_jpg/TqajLKDg1xVKXEeOhOjiaM7hS1IuVpzptUQztM8L2LtafVPjJZsDibLq4GQ5ibuWZ1Au8ox2EvBbms3KwU4cqicaNg/0?wx_fmt=jpeg",
  "digest": "最前沿的新闻速递，包括目前有一份 Notion 文档收录了 26 场 正在泰国发生的深度活动...",
  "publishTime": "2024-10-09 14:05:56",
  "categories": [
    "Web3",
    "以太坊",
    "区块链"
  ],
  "url": "https://mp.weixin.qq.com/s?__biz=MzI3NDAzMjkwNg==&mid=undefined&idx=undefined&sn=undefined"
}
