{
  "id": "2648432921_2",
  "title": "SeeDAO｜CFTC 起诉币安，殃及整个加密圈？",
  "author": "翻译公会 雪人",
  "link": "https://mp.weixin.qq.com/s/R4o8i3CkwxO5-1Gd-y1Sxg",
  "cover": "https://mmbiz.qlogo.cn/sz_mmbiz_jpg/TqajLKDg1xWsIfJhSl98MVYzQF6RVNISbeztMzJUIGM7BeNTKnUTWmnZj9ic7uhia31S9X9pucibJrcicibZvzExzLA/0?wx_fmt=jpeg",
  "digest": "币安要凉？",
  "publishTime": "2023-07-10 15:21:01",
  "categories": [
    "Web3",
    "交易所",
    "crypto",
    "SeeDAO",
    "SeeDAO翻译公会"
  ],
  "url": "https://mp.weixin.qq.com/s?__biz=MzI3NDAzMjkwNg==&mid=undefined&idx=undefined&sn=undefined"
}
