{
  "id": "2648455242_1",
  "title": "SeeDAO | 卧虎藏龙S1E03：DAO之道（上）",
  "author": "CHINESE3卧虎藏龙",
  "link": "https://mp.weixin.qq.com/s/muzB2hWvorYCa01aUsirEQ",
  "cover": "https://mmbiz.qpic.cn/sz_mmbiz_jpg/TqajLKDg1xXDg9CBXgeGPV1FHT5lzJB0diaZC1Nbgibq2ldXcmLNe0WMO2GWjaU0tekgbYQ34hRo7VbdAYlkSOrg/0?wx_fmt=jpeg",
  "digest": "探讨DAO的治理。",
  "publishTime": "2024-05-17 12:19:55",
  "categories": [],
  "url": "https://mp.weixin.qq.com/s?__biz=MzI3NDAzMjkwNg==&mid=undefined&idx=undefined&sn=undefined"
}
