{
  "id": "2648431311_2",
  "title": "给小白的 web3 入门指南",
  "author": "SeeDAO",
  "link": "https://mp.weixin.qq.com/s/uj1NnHC3gYOBTN3lcLw1Ug",
  "cover": "https://mmbiz.qpic.cn/sz_mmbiz_jpg/TqajLKDg1xW8P98Y5QpgaVddF98uDpKlD2AU1NWHV24sVuIaj7bCgOJSLibNT6tXU53sqVf4VibXSlgMqNupaf8A/0?wx_fmt=jpeg",
  "digest": "“SeeDAO 新手成长营将会是你的选择”",
  "publishTime": "2023-06-12 10:53:33",
  "categories": [
    "Web3",
    "社区",
    "#seedao"
  ],
  "url": "https://mp.weixin.qq.com/s?__biz=MzI3NDAzMjkwNg==&mid=undefined&idx=undefined&sn=undefined"
}
