{
  "id": "2648416937_1",
  "title": "DAO贡献者技能三件套：心理建设、自我指导和促进",
  "author": "翻译公会｜bo",
  "link": "https://mp.weixin.qq.com/s/pqqrTSUujrTUDPnYm8sTNA",
  "cover": "https://mmbiz.qlogo.cn/mmbiz_jpg/TqajLKDg1xXpXr6xLLHkMYN6BaogB8yaUs89RONWkCVY3LqM0zEAHBNic8VPYpXIz3KJCibwibicTQR7hGY56R17dg/0?wx_fmt=jpeg",
  "digest": "DAO for fun.",
  "publishTime": "2022-05-08 15:55:37",
  "categories": [
    "心理健康",
    "DAO贡献指引",
    "DAO Tooling"
  ],
  "url": "https://mp.weixin.qq.com/s?__biz=MzI3NDAzMjkwNg==&mid=undefined&idx=undefined&sn=undefined"
}
