{
  "id": "2648447014_2",
  "title": "Web3 英语共学：From DAO to Network State",
  "author": "SeeDAO",
  "link": "https://mp.weixin.qq.com/s/ocB4jjQJ6aYuHjRfEC3DWQ",
  "cover": "https://mmbiz.qpic.cn/sz_mmbiz_jpg/TqajLKDg1xXPwNicSAqEpthlSjCH5POUGyLP6keBsuMGIh0lOTs3gIv4PsbCdEk0f6pmLOFrDyEjRzmFy7mtpNw/0?wx_fmt=jpeg",
  "digest": "Vitalik 共读 002 期  SeeDAO × PlanckerDAO",
  "publishTime": "2023-12-08 12:20:26",
  "categories": [
    "Web3",
    "英语"
  ],
  "url": "https://mp.weixin.qq.com/s?__biz=MzI3NDAzMjkwNg==&mid=undefined&idx=undefined&sn=undefined"
}
