{
  "id": "2648426817_1",
  "title": "SeeDAO | Sushi 的法律架构",
  "author": "翻译公会 xunyang",
  "link": "https://mp.weixin.qq.com/s/4pY8Ly0Nu6BnbMw6ZEtxbg",
  "cover": "https://mmbiz.qpic.cn/mmbiz_jpg/TqajLKDg1xX3O2MQQQP8mzAzQiaY9cJ9KN3wJBZp29wGQNjWomSaqegoobYTd2wy9PGoEaPy76kYzichb4CK7hvw/0?wx_fmt=jpeg",
  "digest": "源自 SushiDAO 社区提案",
  "publishTime": "2023-04-06 13:30:40",
  "categories": [
    "DAO",
    "法律"
  ],
  "url": "https://mp.weixin.qq.com/s?__biz=MzI3NDAzMjkwNg==&mid=undefined&idx=undefined&sn=undefined"
}
