{
  "id": "2648456526_1",
  "title": "「北斗计划 · 玉衡」报名启动｜Conflux树图带你走进 Web3 世界",
  "author": "树图区块链",
  "link": "https://mp.weixin.qq.com/s/s8pyt9fRDz67_0FRkxpLyw",
  "cover": "https://mmbiz.qpic.cn/sz_mmbiz_jpg/TqajLKDg1xUiccOuvWXQZDwSGfQ5WIkzNZazK7ib858MIVd2ibzibknm5wC3CPr1TLB43C5874w9DRAPEl2johZQkw/0?wx_fmt=jpeg",
  "digest": "与行业大咖直接交流的机会",
  "publishTime": "2024-09-20 21:30:00",
  "categories": [],
  "url": "https://mp.weixin.qq.com/s?__biz=MzI3NDAzMjkwNg==&mid=undefined&idx=undefined&sn=undefined"
}
